{
  "M1": 1,
  "M2": 2,
  "M3": 3,
  "M4": 4,
  "M5": 5,
  "M6": 6,
  "M7": 7,
  "M8": 8,
  "M9": 9,
  "M10": 10,
  "M11": 11,
  "M12": 12,
  "M13": 13,
  "M14": 14,
  "M15": 15,
  "M16": 16,
  "M17": 17,
  "M18": 18,
  "M19": 19,
  "M20": 20,
  "M21": 21,
  "M22": 22,
  "M23": 23,
  "M24": 24,
  "M25": 25,
  "T1": 26,
  "T2": 27,
  "T3": 28,
  "T4": 29,
  "T5": 30,
  "T6": 31,
  "T7": 32,
  "T8": 33,
  "T9": 34,
  "T10": 35,
  "T11": 36,
  "T12": 37,
  "T13": 38,
  "T14": 39,
  "T15": 40,
  "T16": 41,
  "T17": 42,
  "T18": 43,
  "T19": 44,
  "T20": 45,
  "T21": 46,
  "T22": 47,
  "T23": 48,
  "T24": 49,
  "T25": 50,
  "CON1": 51,
  "CON2": 52,
  "CON3": 53,
  "CON4": 54,
  "CON5": 55,
  "CON6": 56,
  "CON7": 57,
  "CON8": 58,
  "CON9": 59,
  "CON10": 60,
  "CON11": 61,
  "CON12": 62,
  "CON13": 63,
  "CON14": 64,
  "CON15": 65,
  "CON16": 66,
  "CON17": 67,
  "CON18": 68,
  "CON19": 69,
  "CON20": 70,
  "CON21": 71,
  "CON22": 72,
  "CON23": 73,
  "CON24": 74,
  "CON25": 75,
  "V1": 76,
  "V2": 77,
  "V3": 78,
  "V4": 79,
  "V5": 80,
  "V6": 81,
  "V7": 82,
  "V8": 83,
  "V9": 84,
  "V10": 85,
  "V11": 86,
  "V12": 87,
  "V13": 88,
  "V14": 89,
  "V15": 90,
  "V16": 91,
  "V17": 92,
  "V18": 93,
  "V19": 94,
  "V20": 95,
  "V21": 96,
  "V22": 97,
  "V23": 98,
  "V24": 99,
  "V25": 100,
  "PORT1": 101,
  "PORT2": 102,
  "PORT3": 103,
  "PORT4": 104,
  "PORT5": 105,
  "PORT6": 106,
  "PORT7": 107,
  "PORT8": 108,
  "PORT9": 109,
  "PORT10": 110,
  "PORT11": 111,
  "PORT12": 112,
  "PORT13": 113,
  "PORT14": 114,
  "PORT15": 115,
  "PORT16": 116,
  "PORT17": 117,
  "PORT18": 118,
  "PORT19": 119,
  "PORT20": 120,
  "PORT21": 121,
  "PORT22": 122,
  "PORT23": 123,
  "PORT24": 124,
  "PORT25": 125
}